setup.py
ren/__init__.py
ren/lyn.py
ren/ren.py
ren/version.py
ren.egg-info/PKG-INFO
ren.egg-info/SOURCES.txt
ren.egg-info/dependency_links.txt
ren.egg-info/entry_points.txt
ren.egg-info/requires.txt
ren.egg-info/top_level.txt