Metadata-Version: 1.0
Name: ren
Version: 0.6.0
Summary: ren is a command for easily renaming directories and files.
Home-page: https://github.com/heynemann/ren
Author: Bernardo Heynemann
Author-email: heynemann@gmail.com
License: MIT
Keywords: filesystem bash rename mv move
Platform: UNKNOWN
Classifier: Development Status :: 4 - Beta
Classifier: Intended Audience :: Developers
Classifier: License :: OSI Approved :: MIT License
Classifier: Natural Language :: English
Classifier: Operating System :: MacOS
Classifier: Operating System :: POSIX :: Linux
Classifier: Programming Language :: Python :: 2.6
